parse_stages/__init__.py
parse_stages/defs.py
parse_stages/expr.py
parse_stages/p_pyp.py
parse_stages/py.typed
parse_stages-0.1.9.dist-info/METADATA
parse_stages-0.1.9.dist-info/WHEEL
parse_stages-0.1.9.dist-info/RECORD
