Metadata-Version: 2.3
Name: parse_stages
Version: 0.1.9
Summary: Parse an expression for selecting stages and tags
Project-URL: Homepage, https://devel.ringlet.net/devel/parse-stages/
Project-URL: Changes, https://devel.ringlet.net/devel/parse-stages/changes/
Project-URL: Issue Tracker, https://gitlab.com/ppentchev/parse-stages/-/issues
Project-URL: Source Code, https://gitlab.com/ppentchev/parse-stages
Author-email: Peter Pentchev <roam@ringlet.net>
License: BSD-2-Clause
Classifier: Development Status :: 5 - Production/Stable
Classifier: Intended Audience :: Developers
Classifier: License :: DFSG approved
Classifier: License :: Freely Distributable
Classifier: License :: OSI Approved :: BSD License
Classifier: Operating System :: OS Independent
Classifier: Programming Language :: Python
Classifier: Programming Language :: Python :: 3
Classifier: Programming Language :: Python :: 3 :: Only
Classifier: Programming Language :: Python :: 3.10
Classifier: Programming Language :: Python :: 3.11
Classifier: Programming Language :: Python :: 3.12
Classifier: Programming Language :: Python :: 3.13
Classifier: Topic :: Software Development :: Libraries
Classifier: Topic :: Software Development :: Libraries :: Python Modules
Classifier: Topic :: Software Development :: Testing
Classifier: Topic :: Software Development :: Testing :: Unit
Classifier: Typing :: Typed
Requires-Python: >=3.10
Requires-Dist: pyparsing<4,>=3
